LICENSE
README.md
pyproject.toml
src/axolotl/contribs/mit/__init__.py
src/axolotl/contribs/mit/muon.py
src/axolotl/contribs/mit/dion/__init__.py
src/axolotl/contribs/mit/dion/axolotl_.py
src/axolotl/contribs/mit/dion/dion.py
src/axolotl/contribs/mit/dion/opt_utils.py
src/axolotl/contribs/mit/dion/scalar_opts.py
src/axolotl_contribs_mit.egg-info/PKG-INFO
src/axolotl_contribs_mit.egg-info/SOURCES.txt
src/axolotl_contribs_mit.egg-info/dependency_links.txt
src/axolotl_contribs_mit.egg-info/requires.txt
src/axolotl_contribs_mit.egg-info/top_level.txt