Metadata-Version: 2.4
Name: axolotl-contribs-mit
Version: 0.0.4
Summary: MIT contributions to the axolotl framework
Author: Wing Lian
License: MIT License
Classifier: Programming Language :: Python :: 3
License-File: LICENSE
Requires-Dist: torch>=2.4.1
Dynamic: license-file
